[
  {
    "service": "proxmox",
    "baseUrl": "https://proxBig.prox:8006",
    "endpoints": [
      {
        "path": "/nodes/{node}/status",
        "method": "GET",
        "category": "node",
        "readOnly": true,
        "responseSchema": {
          "type": "object",
          "properties": {
            "data": {
              "type": "object",
              "properties": {
                "current-kernel": {
                  "type": "object",
                  "properties": {
                    "machine": {
                      "type": "string"
                    },
                    "release": {
                      "type": "string"
                    },
                    "version": {
                      "type": "string"
                    },
                    "sysname": {
                      "type": "string"
                    }
                  }
                },
                "memory": {
                  "type": "object",
                  "properties": {
                    "total": {
                      "type": "number"
                    },
                    "used": {
                      "type": "number"
                    },
                    "free": {
                      "type": "number"
                    }
                  }
                },
                "pveversion": {
                  "type": "string"
                },
                "ksm": {
                  "type": "object",
                  "properties": {
                    "shared": {
                      "type": "number"
                    }
                  }
                },
                "swap": {
                  "type": "object",
                  "properties": {
                    "free": {
                      "type": "number"
                    },
                    "used": {
                      "type": "number"
                    },
                    "total": {
                      "type": "number"
                    }
                  }
                },
                "cpuinfo": {
                  "type": "object",
                  "properties": {
                    "flags": {
                      "type": "string"
                    },
                    "user_hz": {
                      "type": "number"
                    },
                    "hvm": {
                      "type": "string"
                    },
                    "mhz": {
                      "type": "string"
                    },
                    "cpus": {
                      "type": "number"
                    },
                    "sockets": {
                      "type": "number"
                    },
                    "cores": {
                      "type": "number"
                    },
                    "model": {
                      "type": "string"
                    }
                  }
                },
                "idle": {
                  "type": "number"
                },
                "rootfs": {
                  "type": "object",
                  "properties": {
                    "total": {
                      "type": "number"
                    },
                    "used": {
                      "type": "number"
                    },
                    "free": {
                      "type": "number"
                    },
                    "avail": {
                      "type": "number"
                    }
                  }
                },
                "wait": {
                  "type": "number"
                },
                "loadavg": {
                  "type": "array",
                  "items": {
                    "type": "string"
                  }
                },
                "cpu": {
                  "type": "number"
                },
                "kversion": {
                  "type": "string"
                },
                "boot-info": {
                  "type": "object",
                  "properties": {
                    "secureboot": {
                      "type": "number"
                    },
                    "mode": {
                      "type": "string"
                    }
                  }
                },
                "uptime": {
                  "type": "number"
                }
              }
            }
          }
        }
      },
      {
        "path": "/nodes/{node}/resources",
        "method": "GET",
        "category": "node",
        "readOnly": true
      },
      {
        "path": "/nodes/{node}/qemu",
        "method": "GET",
        "category": "vm",
        "readOnly": true,
        "responseSchema": {
          "type": "object",
          "properties": {
            "data": {
              "type": "array",
              "items": {
                "type": "object",
                "properties": {
                  "disk": {
                    "type": "number"
                  },
                  "name": {
                    "type": "string"
                  },
                  "maxmem": {
                    "type": "number"
                  },
                  "maxdisk": {
                    "type": "number"
                  },
                  "netout": {
                    "type": "number"
                  },
                  "cpus": {
                    "type": "number"
                  },
                  "vmid": {
                    "type": "number"
                  },
                  "diskwrite": {
                    "type": "number"
                  },
                  "pid": {
                    "type": "number"
                  },
                  "uptime": {
                    "type": "number"
                  },
                  "mem": {
                    "type": "number"
                  },
                  "diskread": {
                    "type": "number"
                  },
                  "status": {
                    "type": "string"
                  },
                  "serial": {
                    "type": "number"
                  },
                  "netin": {
                    "type": "number"
                  },
                  "cpu": {
                    "type": "number"
                  }
                }
              }
            }
          }
        }
      },
      {
        "path": "/nodes/{node}/lxc",
        "method": "GET",
        "category": "container",
        "readOnly": true,
        "responseSchema": {
          "type": "object",
          "properties": {
            "data": {
              "type": "array",
              "items": {}
            }
          }
        }
      },
      {
        "path": "/nodes/{node}/storage",
        "method": "GET",
        "category": "storage",
        "readOnly": true,
        "responseSchema": {
          "type": "object",
          "properties": {
            "data": {
              "type": "array",
              "items": {
                "type": "object",
                "properties": {
                  "shared": {
                    "type": "number"
                  },
                  "used_fraction": {
                    "type": "number"
                  },
                  "active": {
                    "type": "number"
                  },
                  "type": {
                    "type": "string"
                  },
                  "content": {
                    "type": "string"
                  },
                  "used": {
                    "type": "number"
                  },
                  "total": {
                    "type": "number"
                  },
                  "enabled": {
                    "type": "number"
                  },
                  "storage": {
                    "type": "string"
                  },
                  "avail": {
                    "type": "number"
                  }
                }
              }
            }
          }
        }
      },
      {
        "path": "/nodes/{node}/network",
        "method": "GET",
        "category": "network",
        "readOnly": true,
        "responseSchema": {
          "type": "object",
          "properties": {
            "data": {
              "type": "array",
              "items": {
                "type": "object",
                "properties": {
                  "priority": {
                    "type": "number"
                  },
                  "bridge_fd": {
                    "type": "string"
                  },
                  "iface": {
                    "type": "string"
                  },
                  "families": {
                    "type": "array",
                    "items": {
                      "type": "string"
                    }
                  },
                  "method": {
                    "type": "string"
                  },
                  "autostart": {
                    "type": "number"
                  },
                  "type": {
                    "type": "string"
                  },
                  "gateway": {
                    "type": "string"
                  },
                  "netmask": {
                    "type": "string"
                  },
                  "bridge_vlan_aware": {
                    "type": "number"
                  },
                  "bridge_stp": {
                    "type": "string"
                  },
                  "active": {
                    "type": "number"
                  },
                  "address": {
                    "type": "string"
                  },
                  "bridge_vids": {
                    "type": "string"
                  },
                  "method6": {
                    "type": "string"
                  },
                  "cidr": {
                    "type": "string"
                  },
                  "bridge_ports": {
                    "type": "string"
                  }
                }
              }
            }
          }
        }
      },
      {
        "path": "/nodes/{node}/services",
        "method": "GET",
        "category": "system",
        "readOnly": true,
        "responseSchema": {
          "type": "object",
          "properties": {
            "data": {
              "type": "array",
              "items": {
                "type": "object",
                "properties": {
                  "active-state": {
                    "type": "string"
                  },
                  "service": {
                    "type": "string"
                  },
                  "state": {
                    "type": "string"
                  },
                  "name": {
                    "type": "string"
                  },
                  "unit-state": {
                    "type": "string"
                  },
                  "desc": {
                    "type": "string"
                  }
                }
              }
            }
          }
        }
      },
      {
        "path": "/nodes/{node}/tasks",
        "method": "GET",
        "category": "system",
        "readOnly": true,
        "responseSchema": {
          "type": "object",
          "properties": {
            "data": {
              "type": "array",
              "items": {
                "type": "object",
                "properties": {
                  "starttime": {
                    "type": "number"
                  },
                  "id": {
                    "type": "string"
                  },
                  "pid": {
                    "type": "number"
                  },
                  "node": {
                    "type": "string"
                  },
                  "endtime": {
                    "type": "number"
                  },
                  "upid": {
                    "type": "string"
                  },
                  "status": {
                    "type": "string"
                  },
                  "pstart": {
                    "type": "number"
                  },
                  "user": {
                    "type": "string"
                  },
                  "type": {
                    "type": "string"
                  }
                }
              }
            },
            "total": {
              "type": "number"
            }
          }
        }
      },
      {
        "path": "/nodes/{node}/disks/list",
        "method": "GET",
        "category": "storage",
        "readOnly": true,
        "responseSchema": {
          "type": "object",
          "properties": {
            "data": {
              "type": "array",
              "items": {
                "type": "object",
                "properties": {
                  "gpt": {
                    "type": "number"
                  },
                  "serial": {
                    "type": "string"
                  },
                  "osdid-list": {
                    "type": "object"
                  },
                  "wwn": {
                    "type": "string"
                  },
                  "type": {
                    "type": "string"
                  },
                  "devpath": {
                    "type": "string"
                  },
                  "model": {
                    "type": "string"
                  },
                  "wearout": {
                    "type": "number"
                  },
                  "health": {
                    "type": "string"
                  },
                  "rpm": {
                    "type": "number"
                  },
                  "osdid": {
                    "type": "number"
                  },
                  "used": {
                    "type": "string"
                  },
                  "by_id_link": {
                    "type": "string"
                  },
                  "vendor": {
                    "type": "string"
                  },
                  "size": {
                    "type": "number"
                  }
                }
              }
            }
          }
        }
      },
      {
        "path": "/nodes/{node}/qemu/{vmid}/status",
        "method": "GET",
        "category": "vm",
        "readOnly": true,
        "responseSchema": {
          "type": "object",
          "properties": {
            "data": {
              "type": "array",
              "items": {
                "type": "object",
                "properties": {
                  "subdir": {
                    "type": "string"
                  }
                }
              }
            }
          }
        }
      },
      {
        "path": "/nodes/{node}/qemu/{vmid}/config",
        "method": "GET",
        "category": "vm",
        "readOnly": true,
        "responseSchema": {
          "type": "object",
          "properties": {
            "data": {
              "type": "object",
              "properties": {
                "meta": {
                  "type": "string"
                },
                "vmgenid": {
                  "type": "string"
                },
                "cores": {
                  "type": "number"
                },
                "vga": {
                  "type": "string"
                },
                "boot": {
                  "type": "string"
                },
                "net0": {
                  "type": "string"
                },
                "template": {
                  "type": "number"
                },
                "ide2": {
                  "type": "string"
                },
                "scsihw": {
                  "type": "string"
                },
                "agent": {
                  "type": "string"
                },
                "name": {
                  "type": "string"
                },
                "memory": {
                  "type": "string"
                },
                "digest": {
                  "type": "string"
                },
                "serial0": {
                  "type": "string"
                },
                "smbios1": {
                  "type": "string"
                },
                "scsi0": {
                  "type": "string"
                },
                "bootdisk": {
                  "type": "string"
                }
              }
            }
          }
        }
      },
      {
        "path": "/nodes/{node}/qemu/{vmid}/snapshot",
        "method": "GET",
        "category": "vm",
        "readOnly": true,
        "responseSchema": {
          "type": "object",
          "properties": {
            "data": {
              "type": "array",
              "items": {
                "type": "object",
                "properties": {
                  "name": {
                    "type": "string"
                  },
                  "digest": {
                    "type": "string"
                  },
                  "description": {
                    "type": "string"
                  },
                  "running": {
                    "type": "number"
                  }
                }
              }
            }
          }
        }
      },
      {
        "path": "/version",
        "method": "GET",
        "category": "system",
        "readOnly": true,
        "responseSchema": {
          "type": "object",
          "properties": {
            "data": {
              "type": "object",
              "properties": {
                "version": {
                  "type": "string"
                },
                "release": {
                  "type": "string"
                },
                "repoid": {
                  "type": "string"
                }
              }
            }
          }
        }
      },
      {
        "path": "/nodes",
        "method": "GET",
        "category": "cluster",
        "readOnly": true,
        "responseSchema": {
          "type": "object",
          "properties": {
            "data": {
              "type": "array",
              "items": {
                "type": "object",
                "properties": {
                  "status": {
                    "type": "string"
                  },
                  "cpu": {
                    "type": "number"
                  },
                  "disk": {
                    "type": "number"
                  },
                  "type": {
                    "type": "string"
                  },
                  "level": {
                    "type": "string"
                  },
                  "uptime": {
                    "type": "number"
                  },
                  "id": {
                    "type": "string"
                  },
                  "maxdisk": {
                    "type": "number"
                  },
                  "ssl_fingerprint": {
                    "type": "string"
                  },
                  "maxmem": {
                    "type": "number"
                  },
                  "maxcpu": {
                    "type": "number"
                  },
                  "node": {
                    "type": "string"
                  },
                  "mem": {
                    "type": "number"
                  }
                }
              }
            }
          }
        }
      },
      {
        "path": "/storage",
        "method": "GET",
        "category": "storage",
        "readOnly": true,
        "responseSchema": {
          "type": "object",
          "properties": {
            "data": {
              "type": "array",
              "items": {
                "type": "object",
                "properties": {
                  "path": {
                    "type": "string"
                  },
                  "type": {
                    "type": "string"
                  },
                  "content": {
                    "type": "string"
                  },
                  "shared": {
                    "type": "number"
                  },
                  "storage": {
                    "type": "string"
                  },
                  "nodes": {
                    "type": "string"
                  },
                  "prune-backups": {
                    "type": "string"
                  },
                  "digest": {
                    "type": "string"
                  }
                }
              }
            }
          }
        }
      },
      {
        "path": "/access/users",
        "method": "GET",
        "category": "access",
        "readOnly": true,
        "responseSchema": {
          "type": "object",
          "properties": {
            "data": {
              "type": "array",
              "items": {
                "type": "object",
                "properties": {
                  "realm-type": {
                    "type": "string"
                  },
                  "userid": {
                    "type": "string"
                  },
                  "expire": {
                    "type": "number"
                  },
                  "enable": {
                    "type": "number"
                  }
                }
              }
            }
          }
        }
      },
      {
        "path": "/access/roles",
        "method": "GET",
        "category": "access",
        "readOnly": true,
        "responseSchema": {
          "type": "object",
          "properties": {
            "data": {
              "type": "array",
              "items": {
                "type": "object",
                "properties": {
                  "roleid": {
                    "type": "string"
                  },
                  "privs": {
                    "type": "string"
                  },
                  "special": {
                    "type": "number"
                  }
                }
              }
            }
          }
        }
      },
      {
        "path": "/access/permissions",
        "method": "GET",
        "category": "access",
        "readOnly": true,
        "responseSchema": {
          "type": "object",
          "properties": {
            "data": {
              "type": "object",
              "properties": {
                "/pool": {
                  "type": "object",
                  "properties": {
                    "Sys.Audit": {
                      "type": "number"
                    },
                    "Datastore.Audit": {
                      "type": "number"
                    },
                    "Pool.Audit": {
                      "type": "number"
                    },
                    "SDN.Audit": {
                      "type": "number"
                    },
                    "Mapping.Audit": {
                      "type": "number"
                    },
                    "VM.Audit": {
                      "type": "number"
                    }
                  }
                },
                "/nodes": {
                  "type": "object",
                  "properties": {
                    "Datastore.Audit": {
                      "type": "number"
                    },
                    "Sys.Audit": {
                      "type": "number"
                    },
                    "Pool.Audit": {
                      "type": "number"
                    },
                    "SDN.Audit": {
                      "type": "number"
                    },
                    "VM.Audit": {
                      "type": "number"
                    },
                    "Mapping.Audit": {
                      "type": "number"
                    }
                  }
                },
                "/vms": {
                  "type": "object",
                  "properties": {
                    "SDN.Audit": {
                      "type": "number"
                    },
                    "Mapping.Audit": {
                      "type": "number"
                    },
                    "VM.Audit": {
                      "type": "number"
                    },
                    "Sys.Audit": {
                      "type": "number"
                    },
                    "Datastore.Audit": {
                      "type": "number"
                    },
                    "Pool.Audit": {
                      "type": "number"
                    }
                  }
                },
                "/sdn": {
                  "type": "object",
                  "properties": {
                    "Pool.Audit": {
                      "type": "number"
                    },
                    "Datastore.Audit": {
                      "type": "number"
                    },
                    "Sys.Audit": {
                      "type": "number"
                    },
                    "VM.Audit": {
                      "type": "number"
                    },
                    "Mapping.Audit": {
                      "type": "number"
                    },
                    "SDN.Audit": {
                      "type": "number"
                    }
                  }
                },
                "/vms/100": {
                  "type": "object",
                  "properties": {
                    "VM.Config.Cloudinit": {
                      "type": "number"
                    },
                    "VM.Console": {
                      "type": "number"
                    },
                    "VM.Config.CDROM": {
                      "type": "number"
                    },
                    "VM.Audit": {
                      "type": "number"
                    },
                    "VM.Monitor": {
                      "type": "number"
                    },
                    "VM.Backup": {
                      "type": "number"
                    },
                    "VM.PowerMgmt": {
                      "type": "number"
                    }
                  }
                },
                "/access": {
                  "type": "object",
                  "properties": {
                    "Datastore.Audit": {
                      "type": "number"
                    },
                    "Sys.Audit": {
                      "type": "number"
                    },
                    "Pool.Audit": {
                      "type": "number"
                    },
                    "SDN.Audit": {
                      "type": "number"
                    },
                    "VM.Audit": {
                      "type": "number"
                    },
                    "Mapping.Audit": {
                      "type": "number"
                    }
                  }
                },
                "/storage": {
                  "type": "object",
                  "properties": {
                    "VM.Audit": {
                      "type": "number"
                    },
                    "Mapping.Audit": {
                      "type": "number"
                    },
                    "SDN.Audit": {
                      "type": "number"
                    },
                    "Pool.Audit": {
                      "type": "number"
                    },
                    "Datastore.Audit": {
                      "type": "number"
                    },
                    "Sys.Audit": {
                      "type": "number"
                    }
                  }
                },
                "/access/groups": {
                  "type": "object",
                  "properties": {
                    "Datastore.Audit": {
                      "type": "number"
                    },
                    "Sys.Audit": {
                      "type": "number"
                    },
                    "Pool.Audit": {
                      "type": "number"
                    },
                    "SDN.Audit": {
                      "type": "number"
                    },
                    "VM.Audit": {
                      "type": "number"
                    },
                    "Mapping.Audit": {
                      "type": "number"
                    }
                  }
                },
                "/": {
                  "type": "object",
                  "properties": {
                    "Pool.Audit": {
                      "type": "number"
                    },
                    "Datastore.Audit": {
                      "type": "number"
                    },
                    "Sys.Audit": {
                      "type": "number"
                    },
                    "VM.Audit": {
                      "type": "number"
                    },
                    "Mapping.Audit": {
                      "type": "number"
                    },
                    "SDN.Audit": {
                      "type": "number"
                    }
                  }
                }
              }
            }
          }
        }
      },
      {
        "path": "/network",
        "method": "GET",
        "category": "network",
        "readOnly": true
      }
    ],
    "discoveredAt": "2025-11-25T01:47:55.196Z",
    "metadata": {
      "isStandalone": true,
      "nodeName": "proxBig",
      "hasGlobalAccess": true
    }
  }
]